iree/build/__init__.py
iree/build/__main__.py
iree/build/args.py
iree/build/compile_actions.py
iree/build/console.py
iree/build/executor.py
iree/build/lang.py
iree/build/main.py
iree/build/metadata.py
iree/build/net_actions.py
iree/build/onnx_actions.py
iree/build/target_machine.py
iree/build/test_actions.py
iree/compiler/__init__.py
iree/compiler/_package_test.py
iree/compiler/ir.py
iree/compiler/passmanager.py
iree/compiler/rewrite.py
iree/compiler/tf.py
iree/compiler/tflite.py
iree/compiler/version.py
iree/compiler/_mlir_libs/__init__.py
iree/compiler/_mlir_libs/_ireeCompilerDialects.cpython-313-darwin.so
iree/compiler/_mlir_libs/_ireeDialects.cpython-313-darwin.so
iree/compiler/_mlir_libs/_mlir.cpython-313-darwin.so
iree/compiler/_mlir_libs/_mlirDialectsAMDGPU.cpython-313-darwin.so
iree/compiler/_mlir_libs/_mlirDialectsGPU.cpython-313-darwin.so
iree/compiler/_mlir_libs/_mlirDialectsLLVM.cpython-313-darwin.so
iree/compiler/_mlir_libs/_mlirDialectsLinalg.cpython-313-darwin.so
iree/compiler/_mlir_libs/_mlirDialectsPDL.cpython-313-darwin.so
iree/compiler/_mlir_libs/_mlirDialectsTransform.cpython-313-darwin.so
iree/compiler/_mlir_libs/_mlirGPUPasses.cpython-313-darwin.so
iree/compiler/_mlir_libs/_mlirLinalgPasses.cpython-313-darwin.so
iree/compiler/_mlir_libs/_mlirTransformInterpreter.cpython-313-darwin.so
iree/compiler/_mlir_libs/_site_initialize_0.cpython-313-darwin.so
iree/compiler/_mlir_libs/iree-compile
iree/compiler/_mlir_libs/iree-link
iree/compiler/_mlir_libs/iree-lld
iree/compiler/_mlir_libs/iree-opt
iree/compiler/_mlir_libs/libIREECompiler.dylib
iree/compiler/_mlir_libs/_mlir/py.typed
iree/compiler/_mlir_libs/_mlir/dialects/pdl.pyi
iree/compiler/_mlir_libs/_mlir/dialects/transform/__init__.pyi
iree/compiler/api/__init__.py
iree/compiler/api/ctypes_dl.py
iree/compiler/dialects/_affine_enum_gen.py
iree/compiler/dialects/_affine_ops_gen.py
iree/compiler/dialects/_amdgpu_enum_gen.py
iree/compiler/dialects/_amdgpu_ops_gen.py
iree_base_compiler-3.10.0.dist-info/METADATA
iree_base_compiler-3.10.0.dist-info/WHEEL
iree_base_compiler-3.10.0.dist-info/entry_points.txt
iree_base_compiler-3.10.0.dist-info/top_level.txt
iree_base_compiler-3.10.0.dist-info/RECORD
