Metadata-Version: 2.4
Name: iree-base-compiler
Version: 3.10.0
Summary: IREE Python Compiler API
Author: IREE Authors
Author-email: iree-technical-discussion@lists.lfaidata.foundation
License: Apache-2.0
Project-URL: homepage, https://iree.dev/
Project-URL: repository, https://github.com/iree-org/iree
Project-URL: documentation, https://iree.dev/reference/bindings/python/
Classifier: Development Status :: 3 - Alpha
Classifier: License :: OSI Approved :: Apache Software License
Classifier: Programming Language :: Python :: 3
Classifier: Programming Language :: Python :: 3.9
Classifier: Programming Language :: Python :: 3.10
Classifier: Programming Language :: Python :: 3.11
Classifier: Programming Language :: Python :: 3.12
Classifier: Programming Language :: Python :: 3.13
Requires-Dist: numpy
Requires-Dist: sympy
Provides-Extra: onnx
Requires-Dist: onnx>=1.16.0; extra == "onnx"
Dynamic: author
Dynamic: author-email
Dynamic: classifier
Dynamic: description
Dynamic: description-content-type
Dynamic: license
Dynamic: project-url
Dynamic: provides-extra
Dynamic: requires-dist
Dynamic: summary
